{
    "channel_name": "bing",
    "features": [
        {
            "feature_name": "AdaptiveCards",
            "external_url": "",
            "facts": [
                {
                    "name": "",
                    "value": "Bing does not render Adaptive Cards.",
                    "detail": "",
                    "url": ""
                }
            ],
            "examples": [
                {
                    "title": "noexample"
                }
            ]
        },
        {
            "feature_name": "Buttons",
            "external_url": "",
            "facts": [
                {
                    "name": "Appearance",
                    "value": "Native Control.",
                    "detail": "",
                    "url": ""
                }
            ],
            "examples": [
                {
                    "title": "noexample"
                }
            ]
        },
        {
            "feature_name": "Carousel",
            "external_url": "",
            "facts": [
                {
                    "name": "Appearance",
                    "value": "Native Control.",
                    "detail": "",
                    "url": ""
                }
            ],
            "examples": [
                {
                    "title": "noexample"
                }
            ]
        },
        {
            "feature_name": "Channeldata",
            "external_url": "",
            "facts": [
                {
                    "name": "",
                    "value": "More channel functionality is accessible from ChannelData.",
                    "detail": "",
                    "url": ""
                }
            ],
            "examples": [
                {
                    "title": "noexample"
                }
            ]
        },
        {
            "feature_name": "Codesample",
            "external_url": "",
            "facts": [
                {
                    "name": "Appearance",
                    "value": "Down-rendered.",
                    "detail": "",
                    "url": ""
                }
            ],
            "examples": [
                {
                    "title": "noexample"
                }
            ]
        },
        {
            "feature_name": "DirectMessage",
            "external_url": "",
            "facts": [
                {
                    "name": "",
                    "value": "Bots can not send messages to single members.",
                    "detail": "",
                    "url": ""
                }
            ],
            "examples": [
                {
                    "title": "noexample"
                }
            ]
        },
        {
            "feature_name": "Document",
            "external_url": "",
            "facts": [
                {
                    "name": "Appearance",
                    "value": "Down-rendered.",
                    "detail": "",
                    "url": ""
                }
            ],
            "examples": [
                {
                    "title": "noexample"
                }
            ]
        },
        {
            "feature_name": "Emoji",
            "external_url": "",
            "facts": [
                {
                    "name": "Appearance",
                    "value": "Bing clients can display emojis.",
                    "detail": "",
                    "url": ""
                }
            ],
            "examples": [
                {
                    "title": "noexample"
                }
            ]
        },
        {
            "feature_name": "GroupChat",
            "external_url": "",
            "facts": [
                {
                    "name": "",
                    "value": "Bots can't be part of a group.",
                    "detail": "",
                    "url": ""
                }
            ],
            "examples": [
                {
                    "title": "noexample"
                }
            ]
        },
        {
            "feature_name": "HeroCard",
            "external_url": "",
            "facts": [
                {
                    "name": "Appearance",
                    "value": "Native Control.",
                    "detail": "",
                    "url": ""
                }
            ],
            "examples": [
                {
                    "title": "noexample"
                }
            ]
        },
        {
            "feature_name": "Images",
            "external_url": "",
            "facts": [
                {
                    "name": "Appearance",
                    "value": "Native Control.",
                    "detail": "",
                    "url": ""
                }
            ],
            "examples": [
                {
                    "title": "noexample"
                }
            ]
        },
        {
            "feature_name": "List",
            "external_url": "",
            "facts": [
                {
                    "name": "Appearance",
                    "value": "Native Control.",
                    "detail": "",
                    "url": ""
                }
            ],
            "examples": [
                {
                    "title": "noexample"
                }
            ]
        },
        {
            "feature_name": "Location",
            "external_url": "",
            "facts": [
                {
                    "name": "",
                    "value": "Bing clients cannot share location.",
                    "detail": "",
                    "url": ""
                }
            ],
            "examples": [
                {
                    "title": "noexample"
                }
            ]
        },
        {
            "feature_name": "Markdown",
            "external_url": "",
            "facts": [
                {
                    "name": "Appearance",
                    "value": "Down-rendered.",
                    "detail": "",
                    "url": ""
                }
            ],
            "examples": [
                {
                    "title": "noexample"
                }
            ]
        },
        {
            "feature_name": "Members",
            "external_url": "",
            "facts": [
                {
                    "name": "",
                    "value": "Bing does not provide conversation members.",
                    "detail": "",
                    "url": ""
                }
            ],
            "examples": [
                {
                    "title": "noexample"
                }
            ]
        },
        {
            "feature_name": "ReceiptCard",
            "external_url": "",
            "facts": [
                {
                    "name": "Appearance",
                    "value": "Native Control.",
                    "detail": "",
                    "url": ""
                }
            ],
            "examples": [
                {
                    "title": "noexample"
                }
            ]
        },
        {
            "feature_name": "SigninCard",
            "external_url": "",
            "facts": [
                {
                    "name": "Appearance",
                    "value": "Native Control.",
                    "detail": "",
                    "url": ""
                }
            ],
            "examples": [
                {
                    "title": "noexample"
                }
            ]
        },
        {
            "feature_name": "SuggestedActions",
            "external_url": "",
            "facts": [
                {
                    "name": "Appearance",
                    "value": "Native Control.",
                    "detail": "",
                    "url": ""
                }
            ],
            "examples": [
                {
                    "title": "noexample"
                }
            ]
        },
        {
            "feature_name": "ThumbnailCard",
            "external_url": "",
            "facts": [
                {
                    "name": "Appearance",
                    "value": "Native Control.",
                    "detail": "",
                    "url": ""
                }
            ],
            "examples": [
                {
                    "title": "noexample"
                }
            ]
        },
        {
            "feature_name": "Typing",
            "external_url": "",
            "facts": [
                {
                    "name": "",
                    "value": "Bing clients display 'Bot is responding' as typing indicator.",
                    "detail": "",
                    "url": ""
                }
            ],
            "examples": [
                {
                    "title": "noexample"
                }
            ]
        },
        {
            "feature_name": "Video",
            "external_url": "",
            "facts": [
                {
                    "name": "Appearance",
                    "value": "Native Control.",
                    "detail": "",
                    "url": ""
                }
            ],
            "examples": [
                {
                    "title": "noexample"
                }
            ]
        }
    ]
}